fscli/__main__.py
fscli/config.py
fscli/set_key.py
FSCLI-3.0.0.dist-info/METADATA
FSCLI-3.0.0.dist-info/WHEEL
FSCLI-3.0.0.dist-info/entry_points.txt
FSCLI-3.0.0.dist-info/top_level.txt
FSCLI-3.0.0.dist-info/RECORD
