Metadata-Version: 2.1
Name: FSCLI
Version: 3.0.0
Summary: FSCLI is a module that simplifies starting, stopping & deleting servers based on server_id and email.
Home-page: https://github.com/fluidstackio/fscli.git
Author: Abhisar Anand, Srinivas Sriram
Author-email: abhisar.muz@gmail.com, srinivassriram06@gmail.com
License: UNKNOWN
Platform: UNKNOWN
Classifier: Programming Language :: Python
Classifier: Programming Language :: Python :: 3
Requires-Dist: requests
